observai/__init__.py
observai/adapters/base.py
observai/adapters/openai.py
observai/core/__init__.py
observai/core/buffer.py
observai/core/constants.py
observai/core/registry.py
observai-0.1.1.dist-info/LICENSE
observai-0.1.1.dist-info/METADATA
observai-0.1.1.dist-info/WHEEL
observai-0.1.1.dist-info/RECORD
