Metadata-Version: 2.3
Name: observai
Version: 0.1.1
Summary: Lightweight SDK to capture, buffer, and report LLM calls (Only OpenAI for Now) for AI audit and monitoring.
License: Apache-2.0
Keywords: ai,sdk,monitoring,openai,audit
Author: Mouhamadou Dia
Author-email: diamohaminsa@gmail.com
Requires-Python: >=3.10,<3.13
Classifier: Development Status :: 4 - Beta
Classifier: Intended Audience :: Developers
Classifier: License :: OSI Approved :: Apache Software License
Classifier: Programming Language :: Python :: 3
Classifier: Programming Language :: Python :: 3.10
Classifier: Programming Language :: Python :: 3.11
Classifier: Programming Language :: Python :: 3.12
Classifier: Topic :: Software Development :: Libraries
Provides-Extra: openai
Requires-Dist: anyio (>=3.7,<4.0)
Requires-Dist: httpx (>=0.24,<0.25)
Requires-Dist: openai (>=1.76.0) ; extra == "openai"
Project-URL: Homepage, https://github.com/methzen/ObservAI
Project-URL: Repository, https://github.com/methzen/ObservAI
